watson/__init__.py
watson/framework/__init__.py
watson/framework/applications.py
watson/framework/bin.py
watson/framework/config.py
watson/framework/controllers.py
watson/framework/events.py
watson/framework/exceptions.py
watson/framework/listeners.py
watson/framework/debug/__init__.py
watson/framework/debug/abc.py
watson/framework/debug/listeners.py
watson/framework/debug/profile.py
watson/framework/debug/toolbar.py
watson/framework/debug/panels/__init__.py
watson/framework/debug/panels/application.py
watson/framework/debug/panels/framework.py
watson/framework/debug/panels/logging.py
watson/framework/debug/panels/profile.py
watson/framework/debug/panels/request.py
watson/framework/debug/views/debug/toolbar.html
watson/framework/debug/views/debug/panels/application.html
watson/framework/debug/views/debug/panels/framework.html
watson/framework/debug/views/debug/panels/logging.html
watson/framework/debug/views/debug/panels/profile.html
watson/framework/debug/views/debug/panels/request.html
watson/framework/i18n/__init__.py
watson/framework/i18n/translate.py
watson/framework/i18n/locales/__init__.py
watson/framework/i18n/locales/en.py
watson/framework/logging/__init__.py
watson/framework/logging/listeners.py
watson/framework/mail/__init__.py
watson/framework/support/__init__.py
watson/framework/support/console/__init__.py
watson/framework/support/console/commands/__init__.py
watson/framework/support/console/commands/development.py
watson/framework/support/console/commands/project.py
watson/framework/support/jinja2/__init__.py
watson/framework/support/jinja2/filters.py
watson/framework/support/jinja2/globals.py
watson/framework/views/__init__.py
watson/framework/views/decorators.py
watson/framework/views/renderers/__init__.py
watson/framework/views/renderers/abc.py
watson/framework/views/renderers/jinja2.py
watson/framework/views/renderers/json.py
watson/framework/views/renderers/xml.py
watson/framework/views/templates/__init__.py
watson_framework-3.5.4.dist-info/AUTHORS
watson_framework-3.5.4.dist-info/LICENSE
watson_framework-3.5.4.dist-info/METADATA
watson_framework-3.5.4.dist-info/WHEEL
watson_framework-3.5.4.dist-info/entry_points.txt
watson_framework-3.5.4.dist-info/top_level.txt
watson_framework-3.5.4.dist-info/RECORD
