Metadata-Version: 2.1
Name: watson-framework
Version: 3.5.4
Summary: A Python 3 web app framework.
Home-page: http://github.com/watsonpy/watson-framework
Author: Simon Coulton
Author-email: simon@bespohk.com
License: Copyright (c) Bespohk and individual contributors.
Requires-Dist: Pygments (==1.6)
Requires-Dist: Jinja2 (>=2.8)
Requires-Dist: watson-cache (>=1.0.1)
Requires-Dist: watson-common (>=1.5.0)
Requires-Dist: watson-console (>=2.0.2)
Requires-Dist: watson-dev (>=3.0.1)
Requires-Dist: watson-di (>=2.2.2)
Requires-Dist: watson-filters (>=1.0.0)
Requires-Dist: watson-form (>=4.0.3)
Requires-Dist: watson-html (>=1.2.0)
Requires-Dist: watson-mail (>=1.2.1)
Requires-Dist: watson-routing (>=1.2.1)
Requires-Dist: watson-validators (>=1.0.2)
Provides-Extra: test
Requires-Dist: pytest ; extra == 'test'
Requires-Dist: pytest-cov ; extra == 'test'
Requires-Dist: coverage ; extra == 'test'
Requires-Dist: coveralls ; extra == 'test'
